coma/__init__.py
coma/dataset.py
coma/evaluate.py
coma/fpscores.pkl.gz
coma/properties.py
coma/sascorer.py
coma/vae.py
mol_coma-2.1.0.dist-info/licenses/LICENSE
mol_coma-2.1.0.dist-info/METADATA
mol_coma-2.1.0.dist-info/WHEEL
mol_coma-2.1.0.dist-info/top_level.txt
mol_coma-2.1.0.dist-info/RECORD
